crystalfontz/__init__.py
crystalfontz/__main__.py
crystalfontz/atx.py
crystalfontz/baud.py
crystalfontz/cli.py
crystalfontz/client.py
crystalfontz/command.py
crystalfontz/config.py
crystalfontz/cursor.py
crystalfontz/device.py
crystalfontz/effects.py
crystalfontz/error.py
crystalfontz/format.py
crystalfontz/gpio.py
crystalfontz/keys.py
crystalfontz/lcd.py
crystalfontz/packet.py
crystalfontz/py.typed
crystalfontz/receiver.py
crystalfontz/report.py
crystalfontz/response.py
crystalfontz/temperature.py
crystalfontz/watchdog.py
crystalfontz/character/__init__.py
crystalfontz/character/constants.py
crystalfontz/character/rom.py
crystalfontz/character/special.py
crystalfontz/dbus/__init__.py
crystalfontz/dbus/__main__.py
crystalfontz/dbus/config.py
crystalfontz/dbus/effects.py
crystalfontz/dbus/error.py
crystalfontz/dbus/interface.py
crystalfontz/dbus/report.py
crystalfontz/dbus/select.py
crystalfontz/dbus/client/__init__.py
crystalfontz/dbus/client/__main__.py
crystalfontz/dbus/client/cli.py
crystalfontz/dbus/domain/__init__.py
crystalfontz/dbus/domain/atx.py
crystalfontz/dbus/domain/base.py
crystalfontz/dbus/domain/baud.py
crystalfontz/dbus/domain/character.py
crystalfontz/dbus/domain/command.py
crystalfontz/dbus/domain/config.py
crystalfontz/dbus/domain/cursor.py
crystalfontz/dbus/domain/device.py
crystalfontz/dbus/domain/gpio.py
crystalfontz/dbus/domain/keys.py
crystalfontz/dbus/domain/lcd.py
crystalfontz/dbus/domain/response.py
crystalfontz/dbus/domain/temperature.py
crystalfontz/dbus/service/__init__.py
crystalfontz/dbus/service/__main__.py
crystalfontz/dbus/service/cli.py
crystalfontz-5.0.0.dist-info/licenses/LICENSE
crystalfontz-5.0.0.dist-info/METADATA
crystalfontz-5.0.0.dist-info/WHEEL
crystalfontz-5.0.0.dist-info/top_level.txt
crystalfontz-5.0.0.dist-info/RECORD
